{
    "1232793380963094664": {
        "id": "1232793380963094664",
        "username": "uro2",
        "avatar": "2352487888c619c456eb653a2a14e1f4",
        "email": "vendinhasdc@gmail.com",
        "access_token": "MTQ3MDg4NzU3OTQxODIzNDkyMA.C6y0Ac4LHDciOtTeCgOoCIBktXkyE9",
        "refresh_token": "3FsEYKVzTuEw7QwPyXdrXVqQMqfASS",
        "ip": "2804:7f5:b0c1:40a0:d69:cbe9:bccb:3903",
        "userDevice": "Mozilla/5.0 (iPhone; CPU iPhone OS 18_7 like Mac OS X) AppleWebKit/605.1.15 (KHTML, like Gecko) Version/26.2 Mobile/15E148 Safari/604.1",
        "verifiedAt": "2026-02-10T22:49:24.489Z"
    },
    "1447028236050759700": {
        "id": "1447028236050759700",
        "username": "oyh1",
        "avatar": "449794cd8c34fac455175c05b8e6abbd",
        "email": "hyhyolyric@gmail.com",
        "access_token": "MTQ3MDg4NzU3OTQxODIzNDkyMA.5eEemIYlQt4vpC2jcs19I4haLAVZZM",
        "refresh_token": "0MDAQC8lxgVLoCf7Sg5hfWeLFh0q4B",
        "ip": "2804:7f5:b0c1:40a0:87ac:6a18:e455:f0d",
        "userDevice": "Mozilla/5.0 (Linux; Android 10; K) AppleWebKit/537.36 (KHTML, like Gecko) Chrome/144.0.0.0 Mobile Safari/537.36",
        "verifiedAt": "2026-02-11T00:47:54.497Z"
    }
}